command_eval/__init__.py
command_eval/__main__.py
command_eval/errors.py
command_eval/application/__init__.py
command_eval/application/command_evaluation.py
command_eval/domain/__init__.py
command_eval/domain/aggregates/__init__.py
command_eval/domain/aggregates/data_file.py
command_eval/domain/aggregates/evaluation.py
command_eval/domain/aggregates/execution.py
command_eval/domain/aggregates/test_case.py
command_eval/domain/aggregates/test_input.py
command_eval/domain/entities/__init__.py
command_eval/domain/entities/data_item.py
command_eval/domain/entities/evaluation_result.py
command_eval/domain/entities/execution_result.py
command_eval/domain/entities/metric_result.py
command_eval/domain/entities/test_case_result.py
command_eval/domain/events/__init__.py
command_eval/domain/events/base_event.py
command_eval/domain/events/command_executed.py
command_eval/domain/events/data_file_loaded.py
command_eval/domain/events/evaluation_completed.py
command_eval/domain/events/test_case_created.py
command_eval/domain/events/test_input_built.py
command_eval/domain/policies/__init__.py
command_eval/domain/policies/command_execution_policy.py
command_eval/domain/policies/data_file_load_policy.py
command_eval/domain/policies/evaluation_execution_policy.py
command_eval/domain/policies/result_output_policy.py
command_eval/domain/policies/test_case_create_policy.py
command_eval/domain/policies/test_input_build_policy.py
command_eval/domain/ports/__init__.py
command_eval/domain/ports/evaluation_port.py
command_eval/domain/ports/execution_port.py
command_eval/domain/ports/result_writer_port.py
command_eval/domain/value_objects/__init__.py
command_eval/domain/value_objects/actual_input_source.py
command_eval/domain/value_objects/evaluation_config.py
command_eval/domain/value_objects/evaluation_spec.py
command_eval/domain/value_objects/evaluation_status.py
command_eval/domain/value_objects/execution_status.py
command_eval/domain/value_objects/expected_source.py
command_eval-0.0.16.dist-info/licenses/LICENSE
command_eval-0.0.16.dist-info/METADATA
command_eval-0.0.16.dist-info/WHEEL
command_eval-0.0.16.dist-info/top_level.txt
command_eval-0.0.16.dist-info/RECORD
