Metadata-Version: 2.4
Name: command-eval
Version: 0.0.16
Summary: command-eval
Author: AkitoshiHashizume
Classifier: Programming Language :: Python :: 3
Classifier: License :: OSI Approved :: MIT License
Classifier: Operating System :: OS Independent
Requires-Python: >=3.7
License-File: LICENSE
Dynamic: license-file
